<odoo>
    <data>
        <record id="sequence_check_inbound" model="ir.sequence">
            <field name="name">check Inbound sequence</field>
            <field name="code">check.inbound.code</field>
            <field name="prefix">/%(range_year)s/</field>
            <field eval="1" name="number_next"/>
            <field eval="1" name="number_increment"/>
            <field eval="True" name="use_date_range"/>
            <field eval="False" name="company_id"/>
            <field name="padding">4</field>
        </record>
     </data>
</odoo>
